forager/__init__.py
forager/exceptions.py
forager-1.15.3.dist-info/LICENSE
forager-1.15.3.dist-info/METADATA
forager-1.15.3.dist-info/WHEEL
forager-1.15.3.dist-info/top_level.txt
forager-1.15.3.dist-info/RECORD
