Metadata-Version: 2.1
Name: forager
Version: 1.15.3
Summary: A utility for finding feeds on websites
Home-page: https://github.com/richardpetithory/forager
Author: Rick Petithory
Author-email: richardpetithory@gmail.com
License: GNU General Public License v3.0
Platform: UNKNOWN
Classifier: Programming Language :: Python
Classifier: Programming Language :: Python :: 2.7
Classifier: Programming Language :: Python :: 3.4
Classifier: Programming Language :: Python :: 3.5
Classifier: Topic :: Internet :: WWW/HTTP :: Indexing/Search
Requires-Dist: beautifulsoup4
Requires-Dist: requests
Requires-Dist: future
